plover_engine_server/__init__.py
plover_engine_server/config.py
plover_engine_server/errors.py
plover_engine_server/example_client_1.py
plover_engine_server/manager.py
plover_engine_server/server.py
plover_engine_server/websocket/__init__.py
plover_engine_server/websocket/example_client.py
plover_engine_server/websocket/routes.py
plover_engine_server/websocket/server.py
plover_engine_server/websocket/views.py
plover_engine_server_2-0.1.2.dist-info/LICENSE.txt
plover_engine_server_2-0.1.2.dist-info/METADATA
plover_engine_server_2-0.1.2.dist-info/WHEEL
plover_engine_server_2-0.1.2.dist-info/entry_points.txt
plover_engine_server_2-0.1.2.dist-info/top_level.txt
plover_engine_server_2-0.1.2.dist-info/zip-safe
plover_engine_server_2-0.1.2.dist-info/RECORD
