Metadata-Version: 2.1
Name: plover_engine_server_2
Version: 0.1.2
Summary: A server for exposing Plover engine events and functionality
Home-page: https://github.com/user202729/plover_websocket_server
Author: Nick Markopoulos
Author-email: nsmarkop@gmail.com
License: GNU General Public License v3 or later (GPLv3+)
Keywords: plover plover_plugin
Classifier: Development Status :: 4 - Beta
Classifier: Environment :: Plugins
Classifier: Intended Audience :: End Users/Desktop
Classifier: License :: OSI Approved :: GNU General Public License v3 or later (GPLv3+)
Classifier: Operating System :: OS Independent
Classifier: Programming Language :: Python :: 3
Classifier: Programming Language :: Python :: 3.6
Classifier: Programming Language :: Python :: 3.7
Classifier: Programming Language :: Python :: 3.8
License-File: LICENSE.txt
Requires-Dist: plover>=4.0.0.dev8
Requires-Dist: aiohttp
Requires-Dist: jsonpickle
